Workbook

Sheet Start Here
B2: VENDLY TCG - VENDOR INVENTORY & SALES TRACKER
B3: Learn to vend. Tools to profit. - vendlytcg.com
B5: WHAT THIS IS | C5: A cost-basis inventory book and sales ledger for card show vendors. Log what you bought and what it cost, log what you sold it for, and the sheet tells you what you actually made - per card, per channel, and per show.
B7: THE 4 TABS YOU USE
B8: 1. Inventory | C8: Every item you own. Type the cost you paid. Total Cost, Est. Profit and Est. Margin calculate themselves.
B9: 2. Sales Log | C9: Every sale. Type the Item ID from Inventory and the sheet pulls the name and your cost basis automatically, then computes profit after fees and shipping.
B10: 3. Show P&L | C10: One row per show. Enter the table fee and travel; gross sales and COGS are pulled from the Sales Log by matching the Show / Event name.
B11: 4. Dashboard | C11: Read-only summary. Inventory value, gross, COGS, fees, net profit, blended margin, and a profit breakdown by channel.
B13: HOW TO START
B14: Step 1 | C14: Delete the yellow EXAMPLE row on Inventory, Sales Log and Show P&L. They are there to show you the expected format - they are counted in the totals until you remove them.
B15: Step 2 | C15: Give every item a unique Item ID (any format - INV-001, PSA-Charizard, whatever). The Sales Log matches on this exact value, so keep it consistent.
B16: Step 3 | C16: Fill Inventory as you buy. Fill Sales Log as you sell. Never retype a cost - the Sales Log looks it up.
B18: COLOR LEGEND
B19: Yellow cells | C19: You type here. These are your inputs.
B20: White cells with borders | C20: You type here too - normal input rows.
B21: Grey / bordered totals | C21: Formulas. Do not overwrite them or the math breaks.
B22: Orange bars | C22: Sheet titles.
B24: HOW THE MATH WORKS
B25: Total Cost | C25: Qty x Unit Cost.
B26: Est. Margin % | C26: (Ask Price - Unit Cost) / Ask Price. Margin on the sale price, not markup on cost.
B27: Gross (Sales Log) | C27: Qty Sold x Sale Price each.
B28: Net Proceeds | C28: Gross - Fees - Shipping. What actually lands in your pocket.
B29: Profit | C29: Net Proceeds - COGS.
B30: Margin % | C30: Profit / Gross.
B31: Show Net Profit | C31: Gross Sales - COGS - Fees - Total Show Costs.
B32: Break-even Gross | C32: The gross sales a show needs just to cover its costs, given the COGS ratio you actually ran. Falls back to Total Costs until that show has sales logged.
B34: CAPACITY | C34: Inventory holds 250 rows, Sales Log 500, Show P&L 50. To add more, select the last data row, copy it, and paste down - the formulas carry.
B36: A NOTE ON TAXES | C36: This tracker is a record-keeping tool, not tax advice. Cost basis and sales records are what your accountant will ask for. California vendors: see the CDTFA section in the Your First Vendor Table guide at vendlytcg.com/guides/first-vendor-table.
B38: VERSION | C38: v1.0

Sheet Inventory
A1: INVENTORY - what you own and what it cost you
A2: Item ID | B2: Item Name | C2: Category | D2: Set / Series | E2: Condition / Grade | F2: Qty | G2: Unit Cost | H2: Total Cost | I2: Market Comp (ea) | J2: Ask Price (ea) | K2: Est. Profit (ea) | L2: Est. Margin % | M2: Status | N2: Location / Bin | O2: Date Acquired | P2: Source | Q2: Notes
A3: INV-001 | B3: Prismatic Evolutions Elite Trainer Box | C3: Elite Trainer Box | D3: Prismatic Evolutions | E3: Sealed | F3: 2 | G3: 42 | H3: =IF($F3="","",$F3*$G3) -> 84 | I3: 68 | J3: 64 | K3: =IF(OR($J3="",$G3=""),"",$J3-$G3) -> 22 | L3: =IF(OR($J3="",$J3=0),"",($J3-$G3)/$J3) -> 0.34375 | M3: In Stock | N3: Bin A | O3: 46215 | P3: Local pickup | Q3: EXAMPLE ROW - delete before you start
H4: =IF($F4="","",$F4*$G4) | K4: =IF(OR($J4="",$G4=""),"",$J4-$G4) | L4: =IF(OR($J4="",$J4=0),"",($J4-$G4)/$J4)
H5: =IF($F5="","",$F5*$G5) | K5: =IF(OR($J5="",$G5=""),"",$J5-$G5) | L5: =IF(OR($J5="",$J5=0),"",($J5-$G5)/$J5)
H6: =IF($F6="","",$F6*$G6) | K6: =IF(OR($J6="",$G6=""),"",$J6-$G6) | L6: =IF(OR($J6="",$J6=0),"",($J6-$G6)/$J6)
H7: =IF($F7="","",$F7*$G7) | K7: =IF(OR($J7="",$G7=""),"",$J7-$G7) | L7: =IF(OR($J7="",$J7=0),"",($J7-$G7)/$J7)
H8: =IF($F8="","",$F8*$G8) | K8: =IF(OR($J8="",$G8=""),"",$J8-$G8) | L8: =IF(OR($J8="",$J8=0),"",($J8-$G8)/$J8)
H9: =IF($F9="","",$F9*$G9) | K9: =IF(OR($J9="",$G9=""),"",$J9-$G9) | L9: =IF(OR($J9="",$J9=0),"",($J9-$G9)/$J9)
H10: =IF($F10="","",$F10*$G10) | K10: =IF(OR($J10="",$G10=""),"",$J10-$G10) | L10: =IF(OR($J10="",$J10=0),"",($J10-$G10)/$J10)
H11: =IF($F11="","",$F11*$G11) | K11: =IF(OR($J11="",$G11=""),"",$J11-$G11) | L11: =IF(OR($J11="",$J11=0),"",($J11-$G11)/$J11)
H12: =IF($F12="","",$F12*$G12) | K12: =IF(OR($J12="",$G12=""),"",$J12-$G12) | L12: =IF(OR($J12="",$J12=0),"",($J12-$G12)/$J12)
H13: =IF($F13="","",$F13*$G13) | K13: =IF(OR($J13="",$G13=""),"",$J13-$G13) | L13: =IF(OR($J13="",$J13=0),"",($J13-$G13)/$J13)
H14: =IF($F14="","",$F14*$G14) | K14: =IF(OR($J14="",$G14=""),"",$J14-$G14) | L14: =IF(OR($J14="",$J14=0),"",($J14-$G14)/$J14)
H15: =IF($F15="","",$F15*$G15) | K15: =IF(OR($J15="",$G15=""),"",$J15-$G15) | L15: =IF(OR($J15="",$J15=0),"",($J15-$G15)/$J15)
... H253: =IF($F253="","",$F253*$G253) | K253: =IF(OR($J253="",$G253=""),"",$J253-$G253) | L253: =IF(OR($J253="",$J253=0),"",($J253-$G253)/$J253)

Sheet Sales Log
A1: SALES LOG - what you sold and what you actually kept
A2: Sale Date | B2: Item ID | C2: Item Name (auto) | D2: Qty Sold | E2: Sale Price (ea) | F2: Gross | G2: Unit Cost (auto) | H2: COGS | I2: Fees | J2: Shipping | K2: Net Proceeds | L2: Profit | M2: Margin % | N2: Channel | O2: Show / Event | P2: Payment Method | Q2: Buyer / Notes
A3: 46222 | B3: INV-001 | C3: =IFERROR(IF($B3="","",INDEX(Inventory!$B$3:$B$253,MATCH($B3,Inventory!$A$3:$A$253,0))),"") -> Prismatic Evolutions Elite Trainer Box | D3: 1 | E3: 64 | F3: =IF($D3="","",$D3*$E3) -> 64 | G3: =IFERROR(IF($B3="","",INDEX(Inventory!$G$3:$G$253,MATCH($B3,Inventory!$A$3:$A$253,0))),"") -> 42 | H3: =IF($D3="","",$D3*IFERROR($G3+0,0)) -> 42 | I3: 0 | J3: 0 | K3: =IF($F3="","",$F3-$I3-$J3) -> 64 | L3: =IF($K3="","",$K3-$H3) -> 22 | M3: =IF(OR($F3="",$F3=0),"",$L3/$F3) -> 0.34375 | N3: Card Show | O3: Inland Empire Card Show | P3: Cash | Q3: EXAMPLE ROW - delete before you start
C4: =IFERROR(IF($B4="","",INDEX(Inventory!$B$3:$B$253,MATCH($B4,Inventory!$A$3:$A$253,0))),"") | F4: =IF($D4="","",$D4*$E4) | G4: =IFERROR(IF($B4="","",INDEX(Inventory!$G$3:$G$253,MATCH($B4,Inventory!$A$3:$A$253,0))),"") | H4: =IF($D4="","",$D4*IFERROR($G4+0,0)) | K4: =IF($F4="","",$F4-$I4-$J4) | L4: =IF($K4="","",$K4-$H4) | M4: =IF(OR($F4="",$F4=0),"",$L4/$F4)
C5: =IFERROR(IF($B5="","",INDEX(Inventory!$B$3:$B$253,MATCH($B5,Inventory!$A$3:$A$253,0))),"") | F5: =IF($D5="","",$D5*$E5) | G5: =IFERROR(IF($B5="","",INDEX(Inventory!$G$3:$G$253,MATCH($B5,Inventory!$A$3:$A$253,0))),"") | H5: =IF($D5="","",$D5*IFERROR($G5+0,0)) | K5: =IF($F5="","",$F5-$I5-$J5) | L5: =IF($K5="","",$K5-$H5) | M5: =IF(OR($F5="",$F5=0),"",$L5/$F5)
C6: =IFERROR(IF($B6="","",INDEX(Inventory!$B$3:$B$253,MATCH($B6,Inventory!$A$3:$A$253,0))),"") | F6: =IF($D6="","",$D6*$E6) | G6: =IFERROR(IF($B6="","",INDEX(Inventory!$G$3:$G$253,MATCH($B6,Inventory!$A$3:$A$253,0))),"") | H6: =IF($D6="","",$D6*IFERROR($G6+0,0)) | K6: =IF($F6="","",$F6-$I6-$J6) | L6: =IF($K6="","",$K6-$H6) | M6: =IF(OR($F6="",$F6=0),"",$L6/$F6)
C7: =IFERROR(IF($B7="","",INDEX(Inventory!$B$3:$B$253,MATCH($B7,Inventory!$A$3:$A$253,0))),"") | F7: =IF($D7="","",$D7*$E7) | G7: =IFERROR(IF($B7="","",INDEX(Inventory!$G$3:$G$253,MATCH($B7,Inventory!$A$3:$A$253,0))),"") | H7: =IF($D7="","",$D7*IFERROR($G7+0,0)) | K7: =IF($F7="","",$F7-$I7-$J7) | L7: =IF($K7="","",$K7-$H7) | M7: =IF(OR($F7="",$F7=0),"",$L7/$F7)
C8: =IFERROR(IF($B8="","",INDEX(Inventory!$B$3:$B$253,MATCH($B8,Inventory!$A$3:$A$253,0))),"") | F8: =IF($D8="","",$D8*$E8) | G8: =IFERROR(IF($B8="","",INDEX(Inventory!$G$3:$G$253,MATCH($B8,Inventory!$A$3:$A$253,0))),"") | H8: =IF($D8="","",$D8*IFERROR($G8+0,0)) | K8: =IF($F8="","",$F8-$I8-$J8) | L8: =IF($K8="","",$K8-$H8) | M8: =IF(OR($F8="",$F8=0),"",$L8/$F8)
C9: =IFERROR(IF($B9="","",INDEX(Inventory!$B$3:$B$253,MATCH($B9,Inventory!$A$3:$A$253,0))),"") | F9: =IF($D9="","",$D9*$E9) | G9: =IFERROR(IF($B9="","",INDEX(Inventory!$G$3:$G$253,MATCH($B9,Inventory!$A$3:$A$253,0))),"") | H9: =IF($D9="","",$D9*IFERROR($G9+0,0)) | K9: =IF($F9="","",$F9-$I9-$J9) | L9: =IF($K9="","",$K9-$H9) | M9: =IF(OR($F9="",$F9=0),"",$L9/$F9)
C10: =IFERROR(IF($B10="","",INDEX(Inventory!$B$3:$B$253,MATCH($B10,Inventory!$A$3:$A$253,0))),"") | F10: =IF($D10="","",$D10*$E10) | G10: =IFERROR(IF($B10="","",INDEX(Inventory!$G$3:$G$253,MATCH($B10,Inventory!$A$3:$A$253,0))),"") | H10: =IF($D10="","",$D10*IFERROR($G10+0,0)) | K10: =IF($F10="","",$F10-$I10-$J10) | L10: =IF($K10="","",$K10-$H10) | M10: =IF(OR($F10="",$F10=0),"",$L10/$F10)
C11: =IFERROR(IF($B11="","",INDEX(Inventory!$B$3:$B$253,MATCH($B11,Inventory!$A$3:$A$253,0))),"") | F11: =IF($D11="","",$D11*$E11) | G11: =IFERROR(IF($B11="","",INDEX(Inventory!$G$3:$G$253,MATCH($B11,Inventory!$A$3:$A$253,0))),"") | H11: =IF($D11="","",$D11*IFERROR($G11+0,0)) | K11: =IF($F11="","",$F11-$I11-$J11) | L11: =IF($K11="","",$K11-$H11) | M11: =IF(OR($F11="",$F11=0),"",$L11/$F11)
C12: =IFERROR(IF($B12="","",INDEX(Inventory!$B$3:$B$253,MATCH($B12,Inventory!$A$3:$A$253,0))),"") | F12: =IF($D12="","",$D12*$E12) | G12: =IFERROR(IF($B12="","",INDEX(Inventory!$G$3:$G$253,MATCH($B12,Inventory!$A$3:$A$253,0))),"") | H12: =IF($D12="","",$D12*IFERROR($G12+0,0)) | K12: =IF($F12="","",$F12-$I12-$J12) | L12: =IF($K12="","",$K12-$H12) | M12: =IF(OR($F12="",$F12=0),"",$L12/$F12)
C13: =IFERROR(IF($B13="","",INDEX(Inventory!$B$3:$B$253,MATCH($B13,Inventory!$A$3:$A$253,0))),"") | F13: =IF($D13="","",$D13*$E13) | G13: =IFERROR(IF($B13="","",INDEX(Inventory!$G$3:$G$253,MATCH($B13,Inventory!$A$3:$A$253,0))),"") | H13: =IF($D13="","",$D13*IFERROR($G13+0,0)) | K13: =IF($F13="","",$F13-$I13-$J13) | L13: =IF($K13="","",$K13-$H13) | M13: =IF(OR($F13="",$F13=0),"",$L13/$F13)
C14: =IFERROR(IF($B14="","",INDEX(Inventory!$B$3:$B$253,MATCH($B14,Inventory!$A$3:$A$253,0))),"") | F14: =IF($D14="","",$D14*$E14) | G14: =IFERROR(IF($B14="","",INDEX(Inventory!$G$3:$G$253,MATCH($B14,Inventory!$A$3:$A$253,0))),"") | H14: =IF($D14="","",$D14*IFERROR($G14+0,0)) | K14: =IF($F14="","",$F14-$I14-$J14) | L14: =IF($K14="","",$K14-$H14) | M14: =IF(OR($F14="",$F14=0),"",$L14/$F14)
C15: =IFERROR(IF($B15="","",INDEX(Inventory!$B$3:$B$253,MATCH($B15,Inventory!$A$3:$A$253,0))),"") | F15: =IF($D15="","",$D15*$E15) | G15: =IFERROR(IF($B15="","",INDEX(Inventory!$G$3:$G$253,MATCH($B15,Inventory!$A$3:$A$253,0))),"") | H15: =IF($D15="","",$D15*IFERROR($G15+0,0)) | K15: =IF($F15="","",$F15-$I15-$J15) | L15: =IF($K15="","",$K15-$H15) | M15: =IF(OR($F15="",$F15=0),"",$L15/$F15)
... C503: =IFERROR(IF($B503="","",INDEX(Inventory!$B$3:$B$253,MATCH($B503,Inventory!$A$3:$A$253,0))),"") | F503: =IF($D503="","",$D503*$E503) | G503: =IFERROR(IF($B503="","",INDEX(Inventory!$G$3:$G$253,MATCH($B503,Inventory!$A$3:$A$253,0))),"") | H503: =IF($D503="","",$D503*IFERROR($G503+0,0)) | K503: =IF($F503="","",$F503-$I503-$J503) | L503: =IF($K503="","",$K503-$H503) | M503: =IF(OR($F503="",$F503=0),"",$L503/$F503)

Sheet Show P&L
A1: SHOW P&L - did that table actually pay for itself?
A2: Show Name | B2: Date | C2: City | D2: Table Fee | E2: Travel / Gas | F2: Food / Lodging | G2: Other Costs | H2: Total Costs | I2: Gross Sales (auto) | J2: COGS (auto) | K2: Fees (auto) | L2: Net Profit | M2: Break-even Gross | N2: Notes
A3: Inland Empire Card Show | B3: 46222 | C3: Ontario, CA | D3: 75 | E3: 22 | F3: 18 | G3: 0 | H3: =IF($A3="","",$D3+$E3+$F3+$G3) -> 115 | I3: =IF($A3="","",SUMIFS('Sales Log'!$F$3:$F$503,'Sales Log'!$O$3:$O$503,$A3)) -> 64 | J3: =IF($A3="","",SUMIFS('Sales Log'!$H$3:$H$503,'Sales Log'!$O$3:$O$503,$A3)) -> 42 | K3: =IF($A3="","",SUMIFS('Sales Log'!$I$3:$I$503,'Sales Log'!$O$3:$O$503,$A3)) -> 0 | L3: =IF($A3="","",$I3-$J3-$K3-$H3) -> -93 | M3: =IF($A3="","",IFERROR($H3/(1-$J3/$I3),$H3)) -> 334.54545 | N3: EXAMPLE ROW - delete before you start
H4: =IF($A4="","",$D4+$E4+$F4+$G4) | I4: =IF($A4="","",SUMIFS('Sales Log'!$F$3:$F$503,'Sales Log'!$O$3:$O$503,$A4)) | J4: =IF($A4="","",SUMIFS('Sales Log'!$H$3:$H$503,'Sales Log'!$O$3:$O$503,$A4)) | K4: =IF($A4="","",SUMIFS('Sales Log'!$I$3:$I$503,'Sales Log'!$O$3:$O$503,$A4)) | L4: =IF($A4="","",$I4-$J4-$K4-$H4) | M4: =IF($A4="","",IFERROR($H4/(1-$J4/$I4),$H4))
H5: =IF($A5="","",$D5+$E5+$F5+$G5) | I5: =IF($A5="","",SUMIFS('Sales Log'!$F$3:$F$503,'Sales Log'!$O$3:$O$503,$A5)) | J5: =IF($A5="","",SUMIFS('Sales Log'!$H$3:$H$503,'Sales Log'!$O$3:$O$503,$A5)) | K5: =IF($A5="","",SUMIFS('Sales Log'!$I$3:$I$503,'Sales Log'!$O$3:$O$503,$A5)) | L5: =IF($A5="","",$I5-$J5-$K5-$H5) | M5: =IF($A5="","",IFERROR($H5/(1-$J5/$I5),$H5))
H6: =IF($A6="","",$D6+$E6+$F6+$G6) | I6: =IF($A6="","",SUMIFS('Sales Log'!$F$3:$F$503,'Sales Log'!$O$3:$O$503,$A6)) | J6: =IF($A6="","",SUMIFS('Sales Log'!$H$3:$H$503,'Sales Log'!$O$3:$O$503,$A6)) | K6: =IF($A6="","",SUMIFS('Sales Log'!$I$3:$I$503,'Sales Log'!$O$3:$O$503,$A6)) | L6: =IF($A6="","",$I6-$J6-$K6-$H6) | M6: =IF($A6="","",IFERROR($H6/(1-$J6/$I6),$H6))
H7: =IF($A7="","",$D7+$E7+$F7+$G7) | I7: =IF($A7="","",SUMIFS('Sales Log'!$F$3:$F$503,'Sales Log'!$O$3:$O$503,$A7)) | J7: =IF($A7="","",SUMIFS('Sales Log'!$H$3:$H$503,'Sales Log'!$O$3:$O$503,$A7)) | K7: =IF($A7="","",SUMIFS('Sales Log'!$I$3:$I$503,'Sales Log'!$O$3:$O$503,$A7)) | L7: =IF($A7="","",$I7-$J7-$K7-$H7) | M7: =IF($A7="","",IFERROR($H7/(1-$J7/$I7),$H7))
H8: =IF($A8="","",$D8+$E8+$F8+$G8) | I8: =IF($A8="","",SUMIFS('Sales Log'!$F$3:$F$503,'Sales Log'!$O$3:$O$503,$A8)) | J8: =IF($A8="","",SUMIFS('Sales Log'!$H$3:$H$503,'Sales Log'!$O$3:$O$503,$A8)) | K8: =IF($A8="","",SUMIFS('Sales Log'!$I$3:$I$503,'Sales Log'!$O$3:$O$503,$A8)) | L8: =IF($A8="","",$I8-$J8-$K8-$H8) | M8: =IF($A8="","",IFERROR($H8/(1-$J8/$I8),$H8))
H9: =IF($A9="","",$D9+$E9+$F9+$G9) | I9: =IF($A9="","",SUMIFS('Sales Log'!$F$3:$F$503,'Sales Log'!$O$3:$O$503,$A9)) | J9: =IF($A9="","",SUMIFS('Sales Log'!$H$3:$H$503,'Sales Log'!$O$3:$O$503,$A9)) | K9: =IF($A9="","",SUMIFS('Sales Log'!$I$3:$I$503,'Sales Log'!$O$3:$O$503,$A9)) | L9: =IF($A9="","",$I9-$J9-$K9-$H9) | M9: =IF($A9="","",IFERROR($H9/(1-$J9/$I9),$H9))
H10: =IF($A10="","",$D10+$E10+$F10+$G10) | I10: =IF($A10="","",SUMIFS('Sales Log'!$F$3:$F$503,'Sales Log'!$O$3:$O$503,$A10)) | J10: =IF($A10="","",SUMIFS('Sales Log'!$H$3:$H$503,'Sales Log'!$O$3:$O$503,$A10)) | K10: =IF($A10="","",SUMIFS('Sales Log'!$I$3:$I$503,'Sales Log'!$O$3:$O$503,$A10)) | L10: =IF($A10="","",$I10-$J10-$K10-$H10) | M10: =IF($A10="","",IFERROR($H10/(1-$J10/$I10),$H10))
H11: =IF($A11="","",$D11+$E11+$F11+$G11) | I11: =IF($A11="","",SUMIFS('Sales Log'!$F$3:$F$503,'Sales Log'!$O$3:$O$503,$A11)) | J11: =IF($A11="","",SUMIFS('Sales Log'!$H$3:$H$503,'Sales Log'!$O$3:$O$503,$A11)) | K11: =IF($A11="","",SUMIFS('Sales Log'!$I$3:$I$503,'Sales Log'!$O$3:$O$503,$A11)) | L11: =IF($A11="","",$I11-$J11-$K11-$H11) | M11: =IF($A11="","",IFERROR($H11/(1-$J11/$I11),$H11))
H12: =IF($A12="","",$D12+$E12+$F12+$G12) | I12: =IF($A12="","",SUMIFS('Sales Log'!$F$3:$F$503,'Sales Log'!$O$3:$O$503,$A12)) | J12: =IF($A12="","",SUMIFS('Sales Log'!$H$3:$H$503,'Sales Log'!$O$3:$O$503,$A12)) | K12: =IF($A12="","",SUMIFS('Sales Log'!$I$3:$I$503,'Sales Log'!$O$3:$O$503,$A12)) | L12: =IF($A12="","",$I12-$J12-$K12-$H12) | M12: =IF($A12="","",IFERROR($H12/(1-$J12/$I12),$H12))
H13: =IF($A13="","",$D13+$E13+$F13+$G13) | I13: =IF($A13="","",SUMIFS('Sales Log'!$F$3:$F$503,'Sales Log'!$O$3:$O$503,$A13)) | J13: =IF($A13="","",SUMIFS('Sales Log'!$H$3:$H$503,'Sales Log'!$O$3:$O$503,$A13)) | K13: =IF($A13="","",SUMIFS('Sales Log'!$I$3:$I$503,'Sales Log'!$O$3:$O$503,$A13)) | L13: =IF($A13="","",$I13-$J13-$K13-$H13) | M13: =IF($A13="","",IFERROR($H13/(1-$J13/$I13),$H13))
H14: =IF($A14="","",$D14+$E14+$F14+$G14) | I14: =IF($A14="","",SUMIFS('Sales Log'!$F$3:$F$503,'Sales Log'!$O$3:$O$503,$A14)) | J14: =IF($A14="","",SUMIFS('Sales Log'!$H$3:$H$503,'Sales Log'!$O$3:$O$503,$A14)) | K14: =IF($A14="","",SUMIFS('Sales Log'!$I$3:$I$503,'Sales Log'!$O$3:$O$503,$A14)) | L14: =IF($A14="","",$I14-$J14-$K14-$H14) | M14: =IF($A14="","",IFERROR($H14/(1-$J14/$I14),$H14))
H15: =IF($A15="","",$D15+$E15+$F15+$G15) | I15: =IF($A15="","",SUMIFS('Sales Log'!$F$3:$F$503,'Sales Log'!$O$3:$O$503,$A15)) | J15: =IF($A15="","",SUMIFS('Sales Log'!$H$3:$H$503,'Sales Log'!$O$3:$O$503,$A15)) | K15: =IF($A15="","",SUMIFS('Sales Log'!$I$3:$I$503,'Sales Log'!$O$3:$O$503,$A15)) | L15: =IF($A15="","",$I15-$J15-$K15-$H15) | M15: =IF($A15="","",IFERROR($H15/(1-$J15/$I15),$H15))
... H53: =IF($A53="","",$D53+$E53+$F53+$G53) | I53: =IF($A53="","",SUMIFS('Sales Log'!$F$3:$F$503,'Sales Log'!$O$3:$O$503,$A53)) | J53: =IF($A53="","",SUMIFS('Sales Log'!$H$3:$H$503,'Sales Log'!$O$3:$O$503,$A53)) | K53: =IF($A53="","",SUMIFS('Sales Log'!$I$3:$I$503,'Sales Log'!$O$3:$O$503,$A53)) | L53: =IF($A53="","",$I53-$J53-$K53-$H53) | M53: =IF($A53="","",IFERROR($H53/(1-$J53/$I53),$H53))

Sheet Dashboard
A1: DASHBOARD - read only, everything here calculates itself
A3: INVENTORY ON HAND | D3: PROFIT BY CHANNEL
A4: Line items | B4: =COUNTA(Inventory!$A$3:$A$253) -> 1 | D4: Channel | E4: Gross | F4: COGS | G4: Fees | H4: Net Profit | I4: Margin %
A5: Total units | B5: =SUM(Inventory!$F$3:$F$253) -> 2 | D5: =IF(Lists!$D$3="","",Lists!$D$3) -> Card Show | E5: =IFERROR(SUMIFS('Sales Log'!$F$3:$F$503,'Sales Log'!$N$3:$N$503,$D5),0) -> 64 | F5: =IFERROR(SUMIFS('Sales Log'!$H$3:$H$503,'Sales Log'!$N$3:$N$503,$D5),0) -> 42 | G5: =IFERROR(SUMIFS('Sales Log'!$I$3:$I$503,'Sales Log'!$N$3:$N$503,$D5),0) -> 0 | H5: =$E5-$F5-$G5 -> 22 | I5: =IFERROR($H5/$E5,"") -> 0.34375
A6: Inventory at cost | B6: =SUM(Inventory!$H$3:$H$253) -> 84 | D6: =IF(Lists!$D$4="","",Lists!$D$4) -> TCGPlayer | E6: =IFERROR(SUMIFS('Sales Log'!$F$3:$F$503,'Sales Log'!$N$3:$N$503,$D6),0) -> 0 | F6: =IFERROR(SUMIFS('Sales Log'!$H$3:$H$503,'Sales Log'!$N$3:$N$503,$D6),0) -> 0 | G6: =IFERROR(SUMIFS('Sales Log'!$I$3:$I$503,'Sales Log'!$N$3:$N$503,$D6),0) -> 0 | H6: =$E6-$F6-$G6 -> 0 | I6: =IFERROR($H6/$E6,"")
A7: Inventory at ask price | B7: =IFERROR(SUMPRODUCT(Inventory!$F$3:$F$253,Inventory!$J$3:$J$253),0) -> 128 | D7: =IF(Lists!$D$5="","",Lists!$D$5) -> eBay | E7: =IFERROR(SUMIFS('Sales Log'!$F$3:$F$503,'Sales Log'!$N$3:$N$503,$D7),0) -> 0 | F7: =IFERROR(SUMIFS('Sales Log'!$H$3:$H$503,'Sales Log'!$N$3:$N$503,$D7),0) -> 0 | G7: =IFERROR(SUMIFS('Sales Log'!$I$3:$I$503,'Sales Log'!$N$3:$N$503,$D7),0) -> 0 | H7: =$E7-$F7-$G7 -> 0 | I7: =IFERROR($H7/$E7,"")
A8: Unrealized profit at ask | B8: =B7-B6 -> 44 | D8: =IF(Lists!$D$6="","",Lists!$D$6) -> Whatnot | E8: =IFERROR(SUMIFS('Sales Log'!$F$3:$F$503,'Sales Log'!$N$3:$N$503,$D8),0) -> 0 | F8: =IFERROR(SUMIFS('Sales Log'!$H$3:$H$503,'Sales Log'!$N$3:$N$503,$D8),0) -> 0 | G8: =IFERROR(SUMIFS('Sales Log'!$I$3:$I$503,'Sales Log'!$N$3:$N$503,$D8),0) -> 0 | H8: =$E8-$F8-$G8 -> 0 | I8: =IFERROR($H8/$E8,"")
A9: Unrealized margin | B9: =IFERROR(B8/B7,"") -> 0.34375 | D9: =IF(Lists!$D$7="","",Lists!$D$7) -> Facebook | E9: =IFERROR(SUMIFS('Sales Log'!$F$3:$F$503,'Sales Log'!$N$3:$N$503,$D9),0) -> 0 | F9: =IFERROR(SUMIFS('Sales Log'!$H$3:$H$503,'Sales Log'!$N$3:$N$503,$D9),0) -> 0 | G9: =IFERROR(SUMIFS('Sales Log'!$I$3:$I$503,'Sales Log'!$N$3:$N$503,$D9),0) -> 0 | H9: =$E9-$F9-$G9 -> 0 | I9: =IFERROR($H9/$E9,"")
D10: =IF(Lists!$D$8="","",Lists!$D$8) -> Local / Cash | E10: =IFERROR(SUMIFS('Sales Log'!$F$3:$F$503,'Sales Log'!$N$3:$N$503,$D10),0) -> 0 | F10: =IFERROR(SUMIFS('Sales Log'!$H$3:$H$503,'Sales Log'!$N$3:$N$503,$D10),0) -> 0 | G10: =IFERROR(SUMIFS('Sales Log'!$I$3:$I$503,'Sales Log'!$N$3:$N$503,$D10),0) -> 0 | H10: =$E10-$F10-$G10 -> 0 | I10: =IFERROR($H10/$E10,"")
A11: SALES TO DATE | D11: =IF(Lists!$D$9="","",Lists!$D$9) -> Other | E11: =IFERROR(SUMIFS('Sales Log'!$F$3:$F$503,'Sales Log'!$N$3:$N$503,$D11),0) -> 0 | F11: =IFERROR(SUMIFS('Sales Log'!$H$3:$H$503,'Sales Log'!$N$3:$N$503,$D11),0) -> 0 | G11: =IFERROR(SUMIFS('Sales Log'!$I$3:$I$503,'Sales Log'!$N$3:$N$503,$D11),0) -> 0 | H11: =$E11-$F11-$G11 -> 0 | I11: =IFERROR($H11/$E11,"")
A12: Sales logged | B12: =COUNT('Sales Log'!$F$3:$F$503) -> 1 | D12: TOTAL | E12: =SUM(E5:E11) -> 64 | F12: =SUM(F5:F11) -> 42 | G12: =SUM(G5:G11) -> 0 | H12: =SUM(H5:H11) -> 22 | I12: =IFERROR($H12/$E12,"") -> 0.34375
A13: Units sold | B13: =SUM('Sales Log'!$D$3:$D$503) -> 1
A14: Gross sales | B14: =SUM('Sales Log'!$F$3:$F$503) -> 64 | D14: Channel names come from the Lists tab - edit them there and this table follows.
A15: Cost of goods sold | B15: =SUM('Sales Log'!$H$3:$H$503) -> 42
A16: Marketplace fees | B16: =SUM('Sales Log'!$I$3:$I$503) -> 0
A17: Shipping paid | B17: =SUM('Sales Log'!$J$3:$J$503) -> 0
A18: Net profit | B18: =SUM('Sales Log'!$L$3:$L$503) -> 22
A19: Blended margin | B19: =IFERROR(B18/B14,"") -> 0.34375
A20: Avg profit per sale | B20: =IFERROR(B18/B12,"") -> 22
A22: SHOWS
A23: Shows logged | B23: =COUNTA('Show P&L'!$A$3:$A$53) -> 1
A24: Total show costs | B24: =SUM('Show P&L'!$H$3:$H$53) -> 115
A25: Net profit after show costs | B25: =SUM('Show P&L'!$L$3:$L$53) -> -93

Sheet Lists
A1: DROPDOWN LISTS - edit these to match how you actually sell
A2: Category | B2: Condition / Grade | C2: Status | D2: Channel | E2: Payment Method
A3: Sealed Box | B3: Sealed | C3: In Stock | D3: Card Show | E3: Cash
A4: Elite Trainer Box | B4: NM | C4: Listed Online | D4: TCGPlayer | E4: Zelle
A5: Booster Bundle | B5: LP | C5: At Show | D5: eBay | E5: Venmo
A6: Booster Pack | B6: MP | C6: Sold | D6: Whatnot | E6: PayPal
A7: Tin / Collection | B7: HP | C7: Reserved | D7: Facebook | E7: Card / Square
A8: Raw Single | B8: DMG | C8: Returned | D8: Local / Cash | E8: Other
A9: Graded Single | B9: PSA 10 | C9: Grading - Pending | D9: Other
A10: Supplies | B10: PSA 9
A11: Lot / Bulk | B11: PSA 8
A12: Other | B12: BGS 9.5
B13: BGS 9
B14: CGC 10
B15: CGC 9.5
B16: Raw - Ungraded
